votingsys/__init__.py
votingsys/data/__init__.py
votingsys/data/aggregation.py
votingsys/data/ranking.py
votingsys/utils/__init__.py
votingsys/utils/counter.py
votingsys/utils/dataframe.py
votingsys/utils/mapping.py
votingsys/utils/timing.py
votingsys/vote/__init__.py
votingsys/vote/base.py
votingsys/vote/rank.py
votingsys/vote/single_mark.py
votingsys-0.0.1a0.dist-info/METADATA
votingsys-0.0.1a0.dist-info/WHEEL
votingsys-0.0.1a0.dist-info/licenses/LICENSE
votingsys-0.0.1a0.dist-info/RECORD
