Metadata-Version: 2.4
Name: votingsys
Version: 0.0.1a0
Summary: Library for preference (or ranked) voting
Author-email: Thibaut Durand <durand.tibo+gh@gmail.com>
License-Expression: BSD-3-Clause
License-File: LICENSE
Keywords: analysis,data,report
Classifier: Development Status :: 3 - Alpha
Classifier: Intended Audience :: Developers
Classifier: Intended Audience :: Information Technology
Classifier: Intended Audience :: Science/Research
Classifier: Operating System :: POSIX :: Linux
Classifier: Programming Language :: Python :: 3.10
Classifier: Programming Language :: Python :: 3.11
Classifier: Programming Language :: Python :: 3.12
Classifier: Programming Language :: Python :: 3.13
Classifier: Topic :: Scientific/Engineering
Classifier: Topic :: Scientific/Engineering :: Artificial Intelligence
Classifier: Topic :: Software Development :: Libraries
Requires-Python: >=3.10
Requires-Dist: coola<1.0,>=0.9.0
Requires-Dist: numpy<3.0,>=2.0
Requires-Dist: polars<2.0,>=1.0
